pyobis/__init__.py
pyobis/_version.py
pyobis/obisutils.py
pyobis/cache/__init__.py
pyobis/cache/cache.py
pyobis/cache/test_cache.py
pyobis/checklist/__init__.py
pyobis/checklist/checklist.py
pyobis/checklist/test_checklist.py
pyobis/dataset/__init__.py
pyobis/dataset/dataset.py
pyobis/dataset/test_dataset.py
pyobis/nodes/__init__.py
pyobis/nodes/nodes.py
pyobis/nodes/test_nodes.py
pyobis/occurrences/__init__.py
pyobis/occurrences/occurrences.py
pyobis/occurrences/test_occurrence.py
pyobis/taxa/__init__.py
pyobis/taxa/taxa.py
pyobis/taxa/test_taxa.py
pyobis-1.6.1.dist-info/licenses/LICENSE
pyobis-1.6.1.dist-info/METADATA
pyobis-1.6.1.dist-info/WHEEL
pyobis-1.6.1.dist-info/top_level.txt
pyobis-1.6.1.dist-info/RECORD
