Metadata-Version: 2.4
Name: pyobis
Version: 1.6.1
Summary: Python client for OBIS
Home-page: https://github.com/iobis/pyobis
Author: pyOBIS Community
Author-email: pyobis-mailing-list@googlegroups.com
License: MIT
Project-URL: Documentation, https://iobis.github.io/pyobis
Project-URL: Bug Tracker, https://github.com/iobis/pyobis
Project-URL: Source Code, https://github.com/iobis/pyobis
Classifier: Development Status :: 5 - Production/Stable
Classifier: Intended Audience :: Science/Research
Classifier: License :: OSI Approved :: MIT License
Classifier: Operating System :: OS Independent
Classifier: Natural Language :: English
Classifier: Programming Language :: Python :: 3
Classifier: Topic :: Scientific/Engineering :: Bio-Informatics
Requires-Python: >=3.7
License-File: LICENSE
Requires-Dist: requests>2.7
Requires-Dist: pandas
Requires-Dist: requests-cache<2.0.0,>=1.2.0
Dynamic: license-file
